esb/__init__.py
esb/__main__.py
esb/cli.py
esb/config.py
esb/blank/.gitignore
esb/blank/README.md
esb/blank/REPORT.md
esb/boilers/elixir/spec.json
esb/boilers/elixir/base/.formatter.exs
esb/boilers/elixir/base/.gitignore
esb/boilers/elixir/base/mix.exs
esb/boilers/elixir/template/lib/main.ex
esb/boilers/go/spec.json
esb/boilers/go/template/go.mod
esb/boilers/go/template/main.go
esb/boilers/python/spec.json
esb/boilers/python/template/main.py
esb/boilers/rust/spec.json
esb/boilers/rust/base/.gitignore
esb/boilers/rust/base/Cargo.toml
esb/boilers/rust/template/src/main.rs
esb/commands/__init__.py
esb/commands/base.py
esb/commands/dashboard.py
esb/commands/fetch.py
esb/commands/init.py
esb/commands/run.py
esb/commands/show.py
esb/commands/start.py
esb/commands/status.py
esb/commands/test.py
esb/lib/__init__.py
esb/lib/boiler.py
esb/lib/dash.py
esb/lib/db.py
esb/lib/fetch.py
esb/lib/langs.py
esb/lib/paths.py
esb/protocol/__init__.py
esb/protocol/fireplace.py
esb/protocol/metric_prefix.py
esb-0.2.0.dist-info/METADATA
esb-0.2.0.dist-info/WHEEL
esb-0.2.0.dist-info/entry_points.txt
esb-0.2.0.dist-info/licenses/LICENSE.md
esb-0.2.0.dist-info/RECORD
