Metadata-Version: 2.3
Name: esb
Version: 0.2.0
Summary: Script your way to rescue Christmas as part of the ElfScript Brigade team.
Project-URL: Documentation, https://github.com/luxedo/esb/README.md
Project-URL: Repository, https://github.com/luxedo/esb.git
Project-URL: Issues, https://github.com/luxedo/esb/issues
Project-URL: Source, https://github.com/luxedo/esb
Author-email: Luiz Eduardo Amaral <luizamaral306@gmail.com>
Maintainer-email: Luiz Eduardo Amaral <luizamaral306@gmail.com>
License: ### GNU GENERAL PUBLIC LICENSE
License-File: LICENSE.md
Keywords: Advent of Code,AoC,CLI,Elf,ElfScript Brigade,Elves
Classifier: Development Status :: 4 - Beta
Classifier: Environment :: Console
Classifier: Intended Audience :: Developers
Classifier: License :: OSI Approved :: GNU General Public License v3 (GPLv3)
Classifier: Programming Language :: Python
Classifier: Programming Language :: Python :: 3.11
Classifier: Programming Language :: Python :: 3.12
Classifier: Programming Language :: Python :: Implementation :: CPython
Classifier: Programming Language :: Python :: Implementation :: PyPy
Classifier: Topic :: Software Development :: Code Generators
Requires-Python: >=3.11
Requires-Dist: beautifulsoup4==4.12.3
Requires-Dist: plotext==5.3.2
Requires-Dist: rich==13.7.0
